Workbook

Sheet installation
A1: ID | B1: Item | C1: Kind | D1: Value | E1: Unit | F1: Calculation | G1: Assumption / source
A2: pet_raw | B2: PET raw materials | C2: Input | D2: 740000 | E2: EUR | G2: User input; materials cost, not selling price.
A3: camera_raw | B3: Compton camera | C3: Input | D3: 100000 | E3: EUR | G3: Order-of-magnitude project estimate.
A4: raw_budget | B4: Complete raw hardware budget | C4: Input | D4: 1000000 | E4: EUR | G4: User-agreed rounded budget including PET, camera and computing.
A5: other_raw | B5: Computing, other hardware and raw-cost allowance | C5: Derived | D5: =(('installation'!D4-'installation'!D2)-'installation'!D3) -> 160000 | E5: EUR | F5: raw_budget-pet_raw-camera_raw | G5: Residual allowance, not a supplier quote.
A6: delivery_extra | B6: Assembly, integration, software deployment, installation, validation and warranty | C6: Input | D6: 200000 | E6: EUR | G6: User-agreed aggregate; excludes central product development and major building works.
A7: delivered_cost | B7: Total delivered cost | C7: Derived | D7: =('installation'!D4+'installation'!D6) -> 1200000 | E7: EUR | F7: raw_budget+delivery_extra
A8: installation_target_margin | B8: Target gross margin | C8: Input | D8: 0.4 | E8: fraction | G8: Historical 40% pricing reference; current commercial price is an independent input.
A9: installation_target_price | B9: Price at target margin | C9: Derived | D9: =('installation'!D7/(1-'installation'!D8)) -> 2000000 | E9: EUR | F9: delivered_cost/(1-installation_target_margin)
A10: installation_price | B10: Installed system price | C10: Input | D10: 2500000 | E10: EUR | G10: Excludes VAT; includes initial software licence and standard commissioning.
A11: installation_profit | B11: Gross profit per installation | C11: Derived | D11: =('installation'!D10-'installation'!D7) -> 1300000 | E11: EUR | F11: installation_price-delivered_cost | G11: Before central software engineering, R&D, regulatory programme, sales and corporate overhead.
A12: installation_margin | B12: Actual gross margin | C12: Derived | D12: =('installation'!D11/'installation'!D10) -> 0.52 | E12: fraction | F12: installation_profit/installation_price
A13: installation_example_count | B13: Illustrative installed systems | C13: Input | D13: 10 | E13: systems | G13: Volume conversion, not a forecast.
A14: installation_example_revenue | B14: Revenue at illustrative volume | C14: Derived | D14: =('installation'!D13*'installation'!D10) -> 25000000 | E14: EUR | F14: installation_example_count*installation_price
A15: installation_negotiated_price | B15: Negotiated system price scenario | C15: Input | D15: 2200000 | E15: EUR | G15: Price sensitivity; not the target commercial offer.
A16: installation_negotiated_margin | B16: Negotiated system gross margin | C16: Derived | D16: =(('installation'!D15-'installation'!D7)/'installation'!D15) -> 0.45454545 | E16: fraction | F16: (installation_negotiated_price-delivered_cost)/installation_negotiated_price

Sheet installation_market
A1: ID | B1: Item | C1: Kind | D1: Value | E1: Unit | F1: Calculation | G1: Assumption / source
A2: room_order_year | B2: Room order reference year | C2: Input | D2: 2025 | E2: year | G2: https://www.iba-worldwide.com/sites/default/files/2026-03/iba-fy25-results-presentation-en.pdf (p. 13)
A3: iba_orders | B3: IBA room orders | C3: Input | D3: 12 | E3: rooms/year | G3: https://www.iba-worldwide.com/sites/default/files/2026-03/iba-fy25-results-presentation-en.pdf (p. 13)
A4: iba_share | B4: IBA share of room orders | C4: Input | D4: 0.63 | E4: fraction | G4: https://www.iba-worldwide.com/sites/default/files/2026-03/iba-fy25-results-presentation-en.pdf (p. 13); reported share is rounded.
A5: global_orders_estimate | B5: Global room order estimate | C5: Derived | D5: =('installation_market'!D3/'installation_market'!D4) -> 19.047619 | E5: rooms/year | F5: iba_orders/iba_share
A6: global_orders | B6: Rounded global room order basis | C6: Derived | D6: =ROUND('installation_market'!D5,0) -> 19 | E6: rooms/year | F6: round(global_orders_estimate,0) | G6: Round before market calculation to recover the agreed 19-room scenario.
A7: new_adoption | B7: Monitoring uptake in new rooms | C7: Input | D7: 1 | E7: fraction | G7: Full-uptake scenario, not observed adoption. Orders assumed to translate to deliveries at a sustained annual rate.
A8: new_systems | B8: New-room monitoring systems | C8: Derived | D8: =('installation_market'!D6*'installation_market'!D7) -> 19 | E8: systems/year | F8: global_orders*new_adoption
A9: market_ticket | B9: Installed-system selling price | C9: Derived | D9: ='installation'!D10 -> 2500000 | E9: EUR | F9: installation_price
A10: new_revenue | B10: New-room annual system market | C10: Derived | D10: =('installation_market'!D8*'installation_market'!D9) -> 47500000 | E10: EUR/year | F10: new_systems*market_ticket
A11: eligible_rooms | B11: Eligible existing rooms | C11: Input | D11: 300 | E11: rooms | G11: Scenario assumption, not a verified installed-base count; compatibility must be validated.
A12: retrofit_adoption | B12: Annual retrofit uptake | C12: Input | D12: 0.05 | E12: fraction | G12: Scenario assumption.
A13: retrofit_systems | B13: Annual retrofit systems | C13: Derived | D13: =('installation_market'!D11*'installation_market'!D12) -> 15 | E13: systems/year | F13: eligible_rooms*retrofit_adoption
A14: retrofit_revenue | B14: Annual retrofit system market | C14: Derived | D14: =('installation_market'!D13*'installation_market'!D9) -> 37500000 | E14: EUR/year | F14: retrofit_systems*market_ticket
A15: annual_systems | B15: Combined annual installations | C15: Derived | D15: =('installation_market'!D8+'installation_market'!D13) -> 34 | E15: systems/year | F15: new_systems+retrofit_systems
A16: annual_market | B16: Combined annual system market | C16: Derived | D16: =('installation_market'!D10+'installation_market'!D14) -> 85000000 | E16: EUR/year | F16: new_revenue+retrofit_revenue | G16: Addressable scenario, not company revenue or gross profit.
A17: base_potential | B17: One-time eligible installed-base potential | C17: Derived | D17: =('installation_market'!D11*'installation_market'!D9) -> 750000000 | E17: EUR | F17: eligible_rooms*market_ticket | G17: Stock opportunity, not annual revenue; not added to annual market.

Sheet annual_service
A1: ID | B1: Item | C1: Kind | D1: Value | E1: Unit | F1: Calculation | G1: Assumption / source
A2: cryocooler_service | B2: Cryocooler and compressor maintenance reserve | C2: Input | D2: 8000 | E2: EUR/year | G2: Provisional allocation within agreed EUR 30k; no routine liquid nitrogen purchases.
A3: hardware_spares | B3: Detector, electronics and computing spares | C3: Input | D3: 10000 | E3: EUR/year | G3: Provisional allowance; major replacements excluded.
A4: hardware_calibration | B4: Calibration and performance verification | C4: Input | D4: 7000 | E4: EUR/year | G4: Includes service technician labour, distinct from monitoring staff.
A5: hardware_travel | B5: Service travel and transport | C5: Input | D5: 5000 | E5: EUR/year | G5: Provisional allowance.
A6: hardware_annual | B6: Hardware maintenance total | C6: Derived | D6: =((('annual_service'!D2+'annual_service'!D3)+'annual_service'!D4)+'annual_service'!D5) -> 30000 | E6: EUR/year | F6: cryocooler_service+hardware_spares+hardware_calibration+hardware_travel | G6: Agreed baseline EUR 30k; supplier validation remains outstanding.
A7: salary | B7: Dedicated monitoring specialist gross salary | C7: Input | D7: 50000 | E7: EUR/year | G7: Proposed Spanish hiring baseline accepted by user; not a salary survey.
A8: employer_rate | B8: Employer contribution allowance | C8: Input | D8: 0.32 | E8: fraction | G8: Approximation based on Spanish contributions; exact payroll depends on classification. https://www.seg-social.es/wps/portal/wss/internet/Trabajadores/CotizacionRecaudacionTrabajadores/10721/10957/583?changeLanguage=es
A9: employer_cost | B9: Employer contributions | C9: Derived | D9: =('annual_service'!D7*'annual_service'!D8) -> 16000 | E9: EUR/year | F9: salary*employer_rate
A10: employee_cost | B10: Dedicated employee loaded cost | C10: Derived | D10: =('annual_service'!D7+'annual_service'!D9) -> 66000 | E10: EUR/year | F10: salary+employer_cost
A11: relief_rate | B11: Relief coverage allowance | C11: Input | D11: 0.2 | E11: fraction | G11: Budget provision for leave, sickness and training; requires actual qualified cover. One working shift only.
A12: relief_cost | B12: Relief coverage cost | C12: Derived | D12: =('annual_service'!D10*'annual_service'!D11) -> 13200 | E12: EUR/year | F12: employee_cost*relief_rate
A13: personnel_unrounded | B13: Personnel cost before budget rounding | C13: Derived | D13: =('annual_service'!D10+'annual_service'!D12) -> 79200 | E13: EUR/year | F13: employee_cost+relief_cost
A14: personnel_rounding | B14: Personnel rounding increment | C14: Input | D14: 1000 | E14: EUR | G14: Round up to this increment.
A15: personnel_spain | B15: Rounded Spain personnel budget | C15: Derived | D15: =(CEILING(('annual_service'!D13/'annual_service'!D14),1)*'annual_service'!D14) -> 80000 | E15: EUR/year | F15: ceil(personnel_unrounded/personnel_rounding)*personnel_rounding
A16: country_factor | B16: Personnel country correction factor | C16: Input | D16: 1 | E16: factor | G16: Spain baseline; adjust for other markets. Applied only to personnel, not hardware/software.
A17: personnel_annual | B17: Country-adjusted personnel budget | C17: Derived | D17: =('annual_service'!D15*'annual_service'!D16) -> 80000 | E17: EUR/year | F17: personnel_spain*country_factor
A18: software_remote | B18: Secure remote access and monitoring | C18: Input | D18: 2000 | E18: EUR/year | G18: Non-personnel allowance; local installation.
A19: software_backup | B19: Backup software and security certificates | C19: Input | D19: 1000 | E19: EUR/year | G19: Non-personnel allowance.
A20: software_licences | B20: Third-party licences and contingency | C20: Input | D20: 2000 | E20: EUR/year | G20: Non-personnel allowance; no cloud reconstruction or hosting.
A21: software_annual | B21: Software operating expenses | C21: Derived | D21: =(('annual_service'!D18+'annual_service'!D19)+'annual_service'!D20) -> 5000 | E21: EUR/year | F21: software_remote+software_backup+software_licences | G21: Hardware purchased at installation. Hospital supplies electricity/networking. Central software engineer excluded here and budgeted at company level.
A22: service_cost | B22: Direct annual service cost | C22: Derived | D22: =(('annual_service'!D6+'annual_service'!D17)+'annual_service'!D21) -> 115000 | E22: EUR/year | F22: hardware_annual+personnel_annual+software_annual
A23: service_target_margin | B23: Target service gross margin | C23: Input | D23: 0.4 | E23: fraction | G23: Historical 40% pricing reference; current commercial price is an independent input.
A24: service_target_price | B24: Annual price at target margin | C24: Derived | D24: =('annual_service'!D22/(1-'annual_service'!D23)) -> 191666.67 | E24: EUR/year | F24: service_cost/(1-service_target_margin)
A25: service_price | B25: Annual service fee | C25: Input | D25: 250000 | E25: EUR/year | G25: Accepted by user; excludes VAT. Service after included installation warranty; avoid charging twice for warranty coverage.
A26: service_profit | B26: Gross profit per annual contract | C26: Derived | D26: =('annual_service'!D25-'annual_service'!D22) -> 135000 | E26: EUR/year | F26: service_price-service_cost | G26: Before central engineer, expert escalation, management and other company expenses.
A27: service_margin | B27: Actual service gross margin | C27: Derived | D27: =('annual_service'!D26/'annual_service'!D25) -> 0.54 | E27: fraction | F27: service_profit/service_price
A28: service_price_ratio | B28: Annual fee as share of system selling price | C28: Derived | D28: =('annual_service'!D25/'installation'!D10) -> 0.1 | E28: fraction | F28: service_price/installation_price | G28: Comparison with selling price, not manufacturing cost.
A29: service_negotiated_price | B29: Negotiated annual service fee scenario | C29: Input | D29: 200000 | E29: EUR/year | G29: Price sensitivity; agreed scope unchanged.
A30: service_negotiated_margin | B30: Negotiated service gross margin | C30: Derived | D30: =(('annual_service'!D29-'annual_service'!D22)/'annual_service'!D29) -> 0.425 | E30: fraction | F30: (service_negotiated_price-service_cost)/service_negotiated_price

Sheet recurring_market
A1: ID | B1: Item | C1: Kind | D1: Value | E1: Unit | F1: Calculation | G1: Assumption / source
A2: recurring_price | B2: Annual contract price | C2: Derived | D2: ='annual_service'!D25 -> 250000 | E2: EUR/year | F2: service_price
A3: recurring_cost | B3: Annual direct cost per contract | C3: Derived | D3: ='annual_service'!D22 -> 115000 | E3: EUR/year | F3: service_cost
A4: recurring_profit | B4: Annual gross profit per contract | C4: Derived | D4: ='annual_service'!D26 -> 135000 | E4: EUR/year | F4: service_profit
A5: small_contracts | B5: Small scenario: active paying contracts | C5: Input | D5: 10 | E5: contracts | G5: Annual steady-state illustration, not a ramp forecast or market-share claim; all contracts active for a full year.
A6: small_revenue | B6: Small scenario: annual recurring revenue | C6: Derived | D6: =('recurring_market'!D5*'recurring_market'!D2) -> 2500000 | E6: EUR/year | F6: small_contracts*recurring_price
A7: small_cost | B7: Small scenario: annual direct cost | C7: Derived | D7: =('recurring_market'!D5*'recurring_market'!D3) -> 1150000 | E7: EUR/year | F7: small_contracts*recurring_cost
A8: small_profit | B8: Small scenario: annual gross profit | C8: Derived | D8: =('recurring_market'!D5*'recurring_market'!D4) -> 1350000 | E8: EUR/year | F8: small_contracts*recurring_profit | G8: Central company operating expenses excluded; not operating profit.
A9: medium_contracts | B9: Medium scenario: active paying contracts | C9: Input | D9: 100 | E9: contracts | G9: Annual steady-state illustration, not a ramp forecast or market-share claim; all contracts active for a full year.
A10: medium_revenue | B10: Medium scenario: annual recurring revenue | C10: Derived | D10: =('recurring_market'!D9*'recurring_market'!D2) -> 25000000 | E10: EUR/year | F10: medium_contracts*recurring_price
A11: medium_cost | B11: Medium scenario: annual direct cost | C11: Derived | D11: =('recurring_market'!D9*'recurring_market'!D3) -> 11500000 | E11: EUR/year | F11: medium_contracts*recurring_cost
A12: medium_profit | B12: Medium scenario: annual gross profit | C12: Derived | D12: =('recurring_market'!D9*'recurring_market'!D4) -> 13500000 | E12: EUR/year | F12: medium_contracts*recurring_profit | G12: Central company operating expenses excluded; not operating profit.
A13: large_contracts | B13: Large scenario: active paying contracts | C13: Input | D13: 300 | E13: contracts | G13: Annual steady-state illustration, not a ramp forecast or market-share claim; all contracts active for a full year.
A14: large_revenue | B14: Large scenario: annual recurring revenue | C14: Derived | D14: =('recurring_market'!D13*'recurring_market'!D2) -> 75000000 | E14: EUR/year | F14: large_contracts*recurring_price
A15: large_cost | B15: Large scenario: annual direct cost | C15: Derived | D15: =('recurring_market'!D13*'recurring_market'!D3) -> 34500000 | E15: EUR/year | F15: large_contracts*recurring_cost
A16: large_profit | B16: Large scenario: annual gross profit | C16: Derived | D16: =('recurring_market'!D13*'recurring_market'!D4) -> 40500000 | E16: EUR/year | F16: large_contracts*recurring_profit | G16: Central company operating expenses excluded; not operating profit.

Sheet market_growth
A1: ID | B1: Item | C1: Kind | D1: Value | E1: Unit | F1: Calculation | G1: Assumption / source
A2: growth_start_year | B2: Reference year | C2: Input | D2: 2026 | E2: year
A3: growth_base | B3: Provisional operating proton rooms | C3: Input | D3: 300 | E3: rooms | G3: Planning assumption; not a verified inventory or ARGOS-compatible base.
A4: growth_short | B4: First horizon | C4: Input | D4: 10 | E4: years
A5: growth_long | B5: Second horizon | C5: Input | D5: 20 | E5: years
A6: growth_short_year | B6: First projection year | C6: Derived | D6: =('market_growth'!D2+'market_growth'!D4) -> 2036 | E6: year | F6: growth_start_year+growth_short
A7: growth_long_year | B7: Second projection year | C7: Derived | D7: =('market_growth'!D2+'market_growth'!D5) -> 2046 | E7: year | F7: growth_start_year+growth_long
A8: growth_slow | B8: Assumed annual net growth: slow | C8: Input | D8: 0.03 | E8: fraction | G8: Judgement-based scenario; not a fitted forecast or confidence interval.
A9: slow_short | B9: Operating rooms: slow short | C9: Derived | D9: =('market_growth'!D3*((1+'market_growth'!D8)^'market_growth'!D4)) -> 403.17491 | E9: rooms | F9: growth_base*(1+growth_slow)**growth_short
A10: slow_short_shown | B10: Rounded rooms: slow short | C10: Derived | D10: =ROUND('market_growth'!D9,0) -> 403 | E10: rooms | F10: round(slow_short,0)
A11: slow_long | B11: Operating rooms: slow long | C11: Derived | D11: =('market_growth'!D3*((1+'market_growth'!D8)^'market_growth'!D5)) -> 541.83337 | E11: rooms | F11: growth_base*(1+growth_slow)**growth_long
A12: slow_long_shown | B12: Rounded rooms: slow long | C12: Derived | D12: =ROUND('market_growth'!D11,0) -> 542 | E12: rooms | F12: round(slow_long,0)
A13: growth_central | B13: Assumed annual net growth: central | C13: Input | D13: 0.05 | E13: fraction | G13: Judgement-based scenario; not a fitted forecast or confidence interval.
A14: central_short | B14: Operating rooms: central short | C14: Derived | D14: =('market_growth'!D3*((1+'market_growth'!D13)^'market_growth'!D4)) -> 488.66839 | E14: rooms | F14: growth_base*(1+growth_central)**growth_short
A15: central_short_shown | B15: Rounded rooms: central short | C15: Derived | D15: =ROUND('market_growth'!D14,0) -> 489 | E15: rooms | F15: round(central_short,0)
A16: central_long | B16: Operating rooms: central long | C16: Derived | D16: =('market_growth'!D3*((1+'market_growth'!D13)^'market_growth'!D5)) -> 795.98931 | E16: rooms | F16: growth_base*(1+growth_central)**growth_long
A17: central_long_shown | B17: Rounded rooms: central long | C17: Derived | D17: =ROUND('market_growth'!D16,0) -> 796 | E17: rooms | F17: round(central_long,0)
A18: growth_fast | B18: Assumed annual net growth: fast | C18: Input | D18: 0.07 | E18: fraction | G18: Judgement-based scenario; not a fitted forecast or confidence interval.
A19: fast_short | B19: Operating rooms: fast short | C19: Derived | D19: =('market_growth'!D3*((1+'market_growth'!D18)^'market_growth'!D4)) -> 590.14541 | E19: rooms | F19: growth_base*(1+growth_fast)**growth_short
A20: fast_short_shown | B20: Rounded rooms: fast short | C20: Derived | D20: =ROUND('market_growth'!D19,0) -> 590 | E20: rooms | F20: round(fast_short,0)
A21: fast_long | B21: Operating rooms: fast long | C21: Derived | D21: =('market_growth'!D3*((1+'market_growth'!D18)^'market_growth'!D5)) -> 1160.9053 | E21: rooms | F21: growth_base*(1+growth_fast)**growth_long
A22: fast_long_shown | B22: Rounded rooms: fast long | C22: Derived | D22: =ROUND('market_growth'!D21,0) -> 1161 | E22: rooms | F22: round(fast_long,0)
A23: observed_centres | B23: Proton facilities January 2026 | C23: Input | D23: 128 | E23: centres | G23: Yap et al. doi:10.3389/fonc.2026.1791102; PTCOG compilation.
A24: construction_rooms | B24: Listed proton rooms under construction June 2026 | C24: Input | D24: 57 | E24: rooms | G24: Manual PTCOG tally; includes stale/uncertain dates; excludes carbon-only rooms. https://ptcog.online/facilities-under-construction/
A25: recent_iba_orders | B25: IBA H1 2026 room orders | C25: Input | D25: 5 | E25: rooms | G25: IBA H1 2026 presentation p13.
A26: recent_iba_share | B26: IBA H1 2026 reported order share | C26: Input | D26: 0.31 | E26: fraction | G26: https://www.iba-worldwide.com/sites/default/files/2026-08/iba_h1_2026_results_presentation.pdf
A27: recent_global_orders | B27: Implied H1 global room orders | C27: Derived | D27: =ROUND(('market_growth'!D25/'market_growth'!D26),0) -> 16 | E27: rooms | F27: round(recent_iba_orders/recent_iba_share,0)
A28: recent_iba_backlog | B28: IBA H1 2026 equipment projects | C28: Input | D28: 46 | E28: projects | G28: 7 ProteusPLUS and 39 ProteusONE; includes 11 installations underway. Overlaps PTCOG pipeline.

Sheet argos_market
A1: ID | B1: Item | C1: Kind | D1: Value | E1: Unit | F1: Calculation | G1: Assumption / source
A2: tam_price | B2: Price per ARGOS system | C2: Derived | D2: ='installation'!D10 -> 2500000 | E2: EUR | F2: installation_price
A3: tam_fee | B3: Annual service fee | C3: Derived | D3: ='annual_service'!D25 -> 250000 | E3: EUR/year | F3: service_price
A4: tam_short_added | B4: Cumulative net additional rooms | C4: Derived | D4: =('market_growth'!D14-'market_growth'!D3) -> 188.66839 | E4: rooms | F4: central_short-growth_base
A5: tam_short_added_shown | B5: Rounded cumulative net additional rooms | C5: Derived | D5: =ROUND('argos_market'!D4,0) -> 189 | E5: rooms | F5: round(tam_short_added,0)
A6: tam_short_systems | B6: Cumulative system sales potential from net expansion | C6: Derived | D6: =('argos_market'!D4*'argos_market'!D2) -> 4.7167097e+08 | E6: EUR | F6: tam_short_added*tam_price | G6: Full compatibility and adoption; all suppliers; excludes existing-base retrofits and replacement. Uses unrounded projections.
A7: tam_short_services | B7: Annual service potential on entire projected room base | C7: Derived | D7: =('market_growth'!D14*'argos_market'!D3) -> 1.221671e+08 | E7: EUR/year | F7: central_short*tam_fee | G7: Full compatibility and adoption; all projected operating rooms on full-year contracts. All suppliers, not ARGOS company revenue.
A8: tam_long_added | B8: Cumulative net additional rooms | C8: Derived | D8: =('market_growth'!D16-'market_growth'!D3) -> 495.98931 | E8: rooms | F8: central_long-growth_base
A9: tam_long_added_shown | B9: Rounded cumulative net additional rooms | C9: Derived | D9: =ROUND('argos_market'!D8,0) -> 496 | E9: rooms | F9: round(tam_long_added,0)
A10: tam_long_systems | B10: Cumulative system sales potential from net expansion | C10: Derived | D10: =('argos_market'!D8*'argos_market'!D2) -> 1.2399733e+09 | E10: EUR | F10: tam_long_added*tam_price | G10: Full compatibility and adoption; all suppliers; excludes existing-base retrofits and replacement. Uses unrounded projections.
A11: tam_long_services | B11: Annual service potential on entire projected room base | C11: Derived | D11: =('market_growth'!D16*'argos_market'!D3) -> 1.9899733e+08 | E11: EUR/year | F11: central_long*tam_fee | G11: Full compatibility and adoption; all projected operating rooms on full-year contracts. All suppliers, not ARGOS company revenue.
